pydantic_ai_filesystem_sandbox/__init__.py
pydantic_ai_filesystem_sandbox/approval_toolset.py
pydantic_ai_filesystem_sandbox/py.typed
pydantic_ai_filesystem_sandbox/sandbox.py
pydantic_ai_filesystem_sandbox/toolset.py
pydantic_ai_filesystem_sandbox-0.9.0.dist-info/METADATA
pydantic_ai_filesystem_sandbox-0.9.0.dist-info/WHEEL
pydantic_ai_filesystem_sandbox-0.9.0.dist-info/licenses/LICENSE
pydantic_ai_filesystem_sandbox-0.9.0.dist-info/RECORD
