Metadata-Version: 2.4
Name: pydantic-ai-filesystem-sandbox
Version: 0.9.0
Summary: Filesystem sandbox toolset for PydanticAI agents with LLM-friendly errors
Project-URL: Homepage, https://github.com/zby/pydantic-ai-filesystem-sandbox
Project-URL: Repository, https://github.com/zby/pydantic-ai-filesystem-sandbox
Author: Zbigniew Łukasiak
License-Expression: MIT
License-File: LICENSE
Keywords: agent,filesystem,llm,pydantic-ai,sandbox,security,tools
Classifier: Development Status :: 3 - Alpha
Classifier: Intended Audience :: Developers
Classifier: License :: OSI Approved :: MIT License
Classifier: Programming Language :: Python :: 3
Classifier: Programming Language :: Python :: 3.10
Classifier: Programming Language :: Python :: 3.11
Classifier: Programming Language :: Python :: 3.12
Classifier: Programming Language :: Python :: 3.13
Classifier: Topic :: Security
Classifier: Topic :: Software Development :: Libraries :: Python Modules
Requires-Python: >=3.10
Requires-Dist: pydantic-ai-blocking-approval>=0.7.0
Requires-Dist: pydantic-ai>=0.1
Requires-Dist: pydantic>=2.0
